cyberrl/__init__.py
cyberrl/demo.py
cyberrl/agents/__init__.py
cyberrl/agents/bruteforce_agent.py
cyberrl/agents/dqn_agent.py
cyberrl/agents/random_agent.py
cyberrl/envs/__init__.py
cyberrl/envs/action.py
cyberrl/envs/environment.py
cyberrl/envs/gym_env.py
cyberrl/envs/host_vector.py
cyberrl/envs/network.py
cyberrl/envs/observation.py
cyberrl/envs/render.py
cyberrl/envs/state.py
cyberrl/envs/utils.py
cyberrl/scenarios/__init__.py
cyberrl/scenarios/generator.py
cyberrl/scenarios/host.py
cyberrl/scenarios/loader.py
cyberrl/scenarios/scenario.py
cyberrl/scenarios/utils.py
cyberrl/scenarios/benchmark/__init__.py
cyberrl/scenarios/benchmark/enterprise.yaml
cyberrl/scenarios/benchmark/generated.py
cyberrl/scenarios/benchmark/multisite_enterprise.yaml
cyberrl/scenarios/benchmark/onesite_enterprise.yaml
cyberrl/scenarios/benchmark/testag.yaml
cyberrl-0.100.0.dist-info/METADATA
cyberrl-0.100.0.dist-info/WHEEL
cyberrl-0.100.0.dist-info/top_level.txt
cyberrl-0.100.0.dist-info/RECORD
