Metadata-Version: 2.1
Name: cyberrl
Version: 0.100.0
Summary: CyberRL
Home-page: UNKNOWN
Author: DE
Author-email: cyberrldevelopment@gmail.com
License: UNKNOWN
Platform: UNKNOWN
Classifier: Development Status :: 3 - Alpha
Classifier: License :: OSI Approved :: MIT License
Classifier: Programming Language :: Python :: 3
Classifier: Programming Language :: Python :: 3.7
Classifier: Programming Language :: Python :: 3.8
Requires-Python: >=3.7
Requires-Dist: gym (>=0.17)
Requires-Dist: numpy (>=1.18)
Requires-Dist: networkx (>=2.4)
Requires-Dist: matplotlib (>=3.1)
Requires-Dist: pyyaml (>=5.3)
Requires-Dist: prettytable (>=0.7)
Provides-Extra: all
Requires-Dist: torch (>=1.5) ; extra == 'all'
Requires-Dist: tensorboard (>=2.2) ; extra == 'all'
Requires-Dist: sphinx (>=3.0) ; extra == 'all'
Requires-Dist: sphinx-rtd-theme (>=0.4) ; extra == 'all'
Requires-Dist: pytest (>=5.4) ; extra == 'all'
Provides-Extra: docs
Requires-Dist: sphinx (>=3.0) ; extra == 'docs'
Requires-Dist: sphinx-rtd-theme (>=0.4) ; extra == 'docs'
Provides-Extra: dqn
Requires-Dist: torch (>=1.5) ; extra == 'dqn'
Requires-Dist: tensorboard (>=2.2) ; extra == 'dqn'
Provides-Extra: test
Requires-Dist: pytest (>=5.4) ; extra == 'test'
